{
  "version": 1,
  "households": {
    "latestSubmissionTime": "2026-05-28T19:39:54.467180+00:00",
    "count": 9281,
    "lastUpdated": "2026-05-28T19:45:54.564Z",
    "files": [
      "2026-05-23.json",
      "2026-05-24.json",
      "2026-05-25.json",
      "2026-05-26.json",
      "2026-05-27.json",
      "2026-05-28.json"
    ]
  },
  "outside": {
    "latestSubmissionTime": "2026-05-28T19:29:25.126126+00:00",
    "count": 5147,
    "lastUpdated": "2026-05-28T19:47:02.474Z",
    "files": [
      "2026-05-23.json",
      "2026-05-24.json",
      "2026-05-25.json",
      "2026-05-26.json",
      "2026-05-27.json",
      "2026-05-28.json"
    ]
  }
}
