{
  "version": 1,
  "households": {
    "latestSubmissionTime": "2026-05-29T20:30:35.538969+00:00",
    "count": 10032,
    "lastUpdated": "2026-05-29T20:43:09.120Z",
    "files": [
      "2026-05-23.json",
      "2026-05-24.json",
      "2026-05-25.json",
      "2026-05-26.json",
      "2026-05-27.json",
      "2026-05-28.json",
      "2026-05-29.json"
    ]
  },
  "outside": {
    "latestSubmissionTime": "2026-05-29T20:02:34.234628+00:00",
    "count": 5694,
    "lastUpdated": "2026-05-29T20:43:10.178Z",
    "files": [
      "2026-05-23.json",
      "2026-05-24.json",
      "2026-05-25.json",
      "2026-05-26.json",
      "2026-05-27.json",
      "2026-05-28.json",
      "2026-05-29.json"
    ]
  }
}
